[
  {
    "city": "Sarajevo",
    "admin": "Bosnia and Herzegovina, Federation of",
    "sort": "275524"
  },
  {
    "city": "Banja Luka",
    "admin": "Srpska, Republika",
    "sort": "199191"
  },
  {
    "city": "Mostar",
    "admin": "Bosnia and Herzegovina, Federation of",
    "sort": "163067"
  },
  {
    "city": "Bijeljina",
    "admin": "Srpska, Republika",
    "sort": "114663"
  },
  {
    "city": "Tuzla",
    "admin": "Bosnia and Herzegovina, Federation of",
    "sort": "110979"
  },
  {
    "city": "Brčko",
    "admin": "Brcko District",
    "sort": "39893"
  },
  {
    "city": "Prijedor",
    "admin": "Srpska, Republika",
    "sort": "89397"
  },
  {
    "city": "Zenica",
    "admin": "Bosnia and Herzegovina, Federation of",
    "sort": "70553"
  },
  {
    "city": "Doboj",
    "admin": "Srpska, Republika",
    "sort": "68514"
  },
  {
    "city": "Zvornik",
    "admin": "Srpska, Republika",
    "sort": "63686"
  },
  {
    "city": "Sanski Most",
    "admin": "Bosnia and Herzegovina, Federation of",
    "sort": "47359"
  },
  {
    "city": "Lukavac",
    "admin": "Bosnia and Herzegovina, Federation of",
    "sort": "46731"
  },
  {
    "city": "Bihać",
    "admin": "Bosnia and Herzegovina, Federation of",
    "sort": "43007"
  },
  {
    "city": "Bugojno",
    "admin": "Bosnia and Herzegovina, Federation of",
    "sort": "34559"
  },
  {
    "city": "Žepče",
    "admin": "Bosnia and Herzegovina, Federation of",
    "sort": "31582"
  },
  {
    "city": "Trebinje",
    "admin": "Srpska, Republika",
    "sort": "31433"
  },
  {
    "city": "Bosanska Krupa",
    "admin": "Bosnia and Herzegovina, Federation of",
    "sort": "29659"
  },
  {
    "city": "Čapljina",
    "admin": "Bosnia and Herzegovina, Federation of",
    "sort": "28122"
  },
  {
    "city": "Banovići",
    "admin": "",
    "sort": "22773"
  },
  {
    "city": "Breza",
    "admin": "Bosnia and Herzegovina, Federation of",
    "sort": "14564"
  },
  {
    "city": "Derventa",
    "admin": "Srpska, Republika",
    "sort": "12680"
  },
  {
    "city": "Goražde",
    "admin": "Bosnia and Herzegovina, Federation of",
    "sort": "12512"
  },
  {
    "city": "Foča",
    "admin": "Srpska, Republika",
    "sort": "12334"
  },
  {
    "city": "Sapna",
    "admin": "Bosnia and Herzegovina, Federation of",
    "sort": "12136"
  },
  {
    "city": "Jablanica",
    "admin": "Bosnia and Herzegovina, Federation of",
    "sort": "10580"
  },
  {
    "city": "Vareš",
    "admin": "Bosnia and Herzegovina, Federation of",
    "sort": "9556"
  },
  {
    "city": "Livno",
    "admin": "Bosnia and Herzegovina, Federation of",
    "sort": "9045"
  },
  {
    "city": "Bosanski Petrovac",
    "admin": "Bosnia and Herzegovina, Federation of",
    "sort": "7946"
  },
  {
    "city": "Mrkonjić Grad",
    "admin": "Srpska, Republika",
    "sort": "7915"
  },
  {
    "city": "Drvar",
    "admin": "Bosnia and Herzegovina, Federation of",
    "sort": "7506"
  },
  {
    "city": "Velika Kladuša",
    "admin": "Bosnia and Herzegovina, Federation of",
    "sort": "6902"
  },
  {
    "city": "Višegrad",
    "admin": "Srpska, Republika",
    "sort": "5869"
  },
  {
    "city": "Tomislavgrad",
    "admin": "Bosnia and Herzegovina, Federation of",
    "sort": "5760"
  }
]